zarinpal.py
errors/ResponseException.py
errors/__init__.py
resources/Fee.py
resources/Inquiries.py
resources/Payments.py
resources/Refunds.py
resources/Reverses.py
resources/Transactions.py
resources/Unverified.py
resources/Verifications.py
resources/__init__.py
utils/Config.py
utils/Validator.py
utils/__init__.py
zarinpal_py_sdk-0.1.3.dist-info/licenses/LICENSE
zarinpal_py_sdk-0.1.3.dist-info/METADATA
zarinpal_py_sdk-0.1.3.dist-info/WHEEL
zarinpal_py_sdk-0.1.3.dist-info/top_level.txt
zarinpal_py_sdk-0.1.3.dist-info/RECORD
