Metadata-Version: 2.4
Name: zarinpal-py-sdk
Version: 0.1.3
Summary: A Python SDK for Zarinpal Payment Gateway
Home-page: https://github.com/ImanAttary/zarinpal_py_sdk
Author: Iman Attary
Author-email: imanattary@gmail.com
Classifier: Programming Language :: Python :: 3
Classifier: License :: OSI Approved :: MIT License
Classifier: Operating System :: OS Independent
Requires-Python: >=3.12
License-File: LICENSE
Requires-Dist: pytest==8.3.4
Requires-Dist: Requests==2.32.4
Requires-Dist: requests_mock==1.12.1
Requires-Dist: setuptools==75.8.0
Dynamic: author
Dynamic: author-email
Dynamic: classifier
Dynamic: description
Dynamic: description-content-type
Dynamic: home-page
Dynamic: license-file
Dynamic: requires-dist
Dynamic: requires-python
Dynamic: summary
